monominmono/__init__.py
monominmono/check.py
monominmono-0.0.2.dist-info/LICENSE
monominmono-0.0.2.dist-info/METADATA
monominmono-0.0.2.dist-info/WHEEL
monominmono-0.0.2.dist-info/top_level.txt
monominmono-0.0.2.dist-info/RECORD
